aioinsta/__init__.py
aioinsta/challenge.py
aioinsta/client.py
aioinsta/enums.py
aioinsta/exceptions.py
aioinsta/extractors.py
aioinsta/helpers.py
aioinsta/idcodec.py
aioinsta/login.py
aioinsta/media.py
aioinsta/parametrs.py
aioinsta/password.py
aioinsta/request.py
aioinsta/user.py
aioinsta/types/media.py
aioinsta/types/user.py
aioinsta-1.7.dist-info/METADATA
aioinsta-1.7.dist-info/WHEEL
aioinsta-1.7.dist-info/licenses/LICENSE
aioinsta-1.7.dist-info/RECORD
