Metadata-Version: 2.1
Name: aioinsta
Version: 1.7
Summary: Tool for parse instagram data
Project-URL: Homepage, https://github.com/sheldygg/aioinsta
Author: sheldy
License-Expression: MIT
License-File: LICENSE
Classifier: Programming Language :: Python :: 3.9
Classifier: Programming Language :: Python :: 3.10
Requires-Dist: aiohttp
Requires-Dist: pycryptodomex
Requires-Dist: pydantic
